[
    {
        "average": 1.9377291120179372,
        "code": "LeftFOfrontaloperculum",
        "count": 1115,
        "dataType": "SummaryStatistics",
        "max": 2.7346454,
        "min": 1.317453,
        "std": 0.20991457657969856
    },
    {
        "code": "LeftFOfrontaloperculum",
        "dataType": "DatasetStatistic",
        "dataset": {
            "data": {
                "categories": [],
                "header": [
                    1.317453,
                    1.345796848,
                    1.374140696,
                    1.402484544,
                    1.430828392,
                    1.45917224,
                    1.487516088,
                    1.515859936,
                    1.544203784,
                    1.572547632,
                    1.60089148,
                    1.629235328,
                    1.657579176,
                    1.685923024,
                    1.7142668719999998,
                    1.7426107199999998,
                    1.7709545679999998,
                    1.7992984159999998,
                    1.8276422639999998,
                    1.8559861119999999,
                    1.8843299599999999,
                    1.9126738079999999,
                    1.9410176559999999,
                    1.9693615039999999,
                    1.9977053519999999,
                    2.0260492,
                    2.0543930479999997,
                    2.0827368959999997,
                    2.1110807439999997,
                    2.1394245919999997,
                    2.1677684399999997,
                    2.1961122879999997,
                    2.2244561359999997,
                    2.2527999839999997,
                    2.2811438319999997,
                    2.3094876799999997,
                    2.3378315279999997,
                    2.3661753759999997,
                    2.3945192239999997,
                    2.4228630719999997,
                    2.4512069199999997,
                    2.4795507679999997,
                    2.5078946159999997,
                    2.5362384639999997,
                    2.5645823119999998,
                    2.5929261599999998,
                    2.6212700079999998,
                    2.6496138559999998,
                    2.6779577039999998,
                    2.7063015519999998,
                    2.7346454
                ],
                "shape": "vector",
                "value": [
                    1,
                    0,
                    2,
                    2,
                    2,
                    4,
                    8,
                    9,
                    15,
                    11,
                    13,
                    23,
                    25,
                    30,
                    44,
                    43,
                    56,
                    44,
                    65,
                    57,
                    74,
                    52,
                    67,
                    70,
                    56,
                    44,
                    40,
                    41,
                    36,
                    32,
                    21,
                    24,
                    24,
                    10,
                    16,
                    13,
                    10,
                    8,
                    6,
                    2,
                    5,
                    1,
                    2,
                    1,
                    1,
                    3,
                    0,
                    0,
                    0,
                    2
                ]
            },
            "name": "Count"
        },
        "label": "Histogram"
    },
    {
        "code": "LeftFOfrontaloperculum",
        "dataType": "DatasetStatistic",
        "dataset": {
            "data": {
                "categories": [
                    "Male",
                    "Male",
                    "Male",
                    "Male",
                    "Male",
                    "Male",
                    "Male",
                    "Male",
                    "Male",
                    "Male",
                    "Male",
                    "Male",
                    "Male",
                    "Male",
                    "Male",
                    "Male",
                    "Male",
                    "Male",
                    "Male",
                    "Male",
                    "Male",
                    "Male",
                    "Male",
                    "Male",
                    "Male",
                    "Male",
                    "Male",
                    "Male",
                    "Male",
                    "Male",
                    "Male",
                    "Male",
                    "Male",
                    "Male",
                    "Male",
                    "Male",
                    "Male",
                    "Male",
                    "Male",
                    "Male",
                    "Male",
                    "Male",
                    "Male",
                    "Male",
                    "Male",
                    "Male",
                    "Male",
                    "Male",
                    "Male",
                    "Male",
                    "Female",
                    "Female",
                    "Female",
                    "Female",
                    "Female",
                    "Female",
                    "Female",
                    "Female",
                    "Female",
                    "Female",
                    "Female",
                    "Female",
                    "Female",
                    "Female",
                    "Female",
                    "Female",
                    "Female",
                    "Female",
                    "Female",
                    "Female",
                    "Female",
                    "Female",
                    "Female",
                    "Female",
                    "Female",
                    "Female",
                    "Female",
                    "Female",
                    "Female",
                    "Female",
                    "Female",
                    "Female",
                    "Female",
                    "Female",
                    "Female",
                    "Female",
                    "Female",
                    "Female",
                    "Female",
                    "Female",
                    "Female",
                    "Female",
                    "Female",
                    "Female",
                    "Female",
                    "Female",
                    "Female",
                    "Female",
                    "Female",
                    "Female"
                ],
                "header": [
                    1.317453,
                    1.345796848,
                    1.374140696,
                    1.402484544,
                    1.430828392,
                    1.45917224,
                    1.487516088,
                    1.515859936,
                    1.544203784,
                    1.572547632,
                    1.60089148,
                    1.629235328,
                    1.657579176,
                    1.685923024,
                    1.7142668719999998,
                    1.7426107199999998,
                    1.7709545679999998,
                    1.7992984159999998,
                    1.8276422639999998,
                    1.8559861119999999,
                    1.8843299599999999,
                    1.9126738079999999,
                    1.9410176559999999,
                    1.9693615039999999,
                    1.9977053519999999,
                    2.0260492,
                    2.0543930479999997,
                    2.0827368959999997,
                    2.1110807439999997,
                    2.1394245919999997,
                    2.1677684399999997,
                    2.1961122879999997,
                    2.2244561359999997,
                    2.2527999839999997,
                    2.2811438319999997,
                    2.3094876799999997,
                    2.3378315279999997,
                    2.3661753759999997,
                    2.3945192239999997,
                    2.4228630719999997,
                    2.4512069199999997,
                    2.4795507679999997,
                    2.5078946159999997,
                    2.5362384639999997,
                    2.5645823119999998,
                    2.5929261599999998,
                    2.6212700079999998,
                    2.6496138559999998,
                    2.6779577039999998,
                    2.7063015519999998,
                    2.7346454,
                    1.317453,
                    1.345796848,
                    1.374140696,
                    1.402484544,
                    1.430828392,
                    1.45917224,
                    1.487516088,
                    1.515859936,
                    1.544203784,
                    1.572547632,
                    1.60089148,
                    1.629235328,
                    1.657579176,
                    1.685923024,
                    1.7142668719999998,
                    1.7426107199999998,
                    1.7709545679999998,
                    1.7992984159999998,
                    1.8276422639999998,
                    1.8559861119999999,
                    1.8843299599999999,
                    1.9126738079999999,
                    1.9410176559999999,
                    1.9693615039999999,
                    1.9977053519999999,
                    2.0260492,
                    2.0543930479999997,
                    2.0827368959999997,
                    2.1110807439999997,
                    2.1394245919999997,
                    2.1677684399999997,
                    2.1961122879999997,
                    2.2244561359999997,
                    2.2527999839999997,
                    2.2811438319999997,
                    2.3094876799999997,
                    2.3378315279999997,
                    2.3661753759999997,
                    2.3945192239999997,
                    2.4228630719999997,
                    2.4512069199999997,
                    2.4795507679999997,
                    2.5078946159999997,
                    2.5362384639999997,
                    2.5645823119999998,
                    2.5929261599999998,
                    2.6212700079999998,
                    2.6496138559999998,
                    2.6779577039999998,
                    2.7063015519999998,
                    2.7346454
                ],
                "shape": "vector",
                "value": [
                    0,
                    0,
                    0,
                    0,
                    0,
                    0,
                    2,
                    1,
                    5,
                    2,
                    1,
                    8,
                    6,
                    10,
                    10,
                    19,
                    22,
                    17,
                    25,
                    27,
                    37,
                    22,
                    40,
                    43,
                    40,
                    30,
                    26,
                    31,
                    29,
                    26,
                    17,
                    20,
                    18,
                    9,
                    13,
                    13,
                    9,
                    5,
                    4,
                    2,
                    5,
                    1,
                    2,
                    1,
                    1,
                    3,
                    0,
                    0,
                    0,
                    2,
                    1,
                    0,
                    2,
                    2,
                    2,
                    4,
                    6,
                    8,
                    10,
                    9,
                    12,
                    15,
                    19,
                    20,
                    34,
                    24,
                    34,
                    27,
                    40,
                    30,
                    37,
                    30,
                    27,
                    27,
                    16,
                    14,
                    14,
                    10,
                    7,
                    6,
                    4,
                    4,
                    6,
                    1,
                    3,
                    0,
                    1,
                    3,
                    2,
                    0,
                    0,
                    0,
                    0,
                    0,
                    0,
                    0,
                    0,
                    0,
                    0,
                    0
                ]
            },
            "name": "Count"
        },
        "label": "Histogram - PTGENDER"
    },
    {
        "code": "LeftFOfrontaloperculum",
        "dataType": "DatasetStatistic",
        "dataset": {
            "data": {
                "categories": [
                    "CN",
                    "CN",
                    "CN",
                    "CN",
                    "CN",
                    "CN",
                    "CN",
                    "CN",
                    "CN",
                    "CN",
                    "CN",
                    "CN",
                    "CN",
                    "CN",
                    "CN",
                    "CN",
                    "CN",
                    "CN",
                    "CN",
                    "CN",
                    "CN",
                    "CN",
                    "CN",
                    "CN",
                    "CN",
                    "CN",
                    "CN",
                    "CN",
                    "CN",
                    "CN",
                    "CN",
                    "CN",
                    "CN",
                    "CN",
                    "CN",
                    "CN",
                    "CN",
                    "CN",
                    "CN",
                    "CN",
                    "CN",
                    "CN",
                    "CN",
                    "CN",
                    "CN",
                    "CN",
                    "CN",
                    "CN",
                    "CN",
                    "CN",
                    "MCI",
                    "MCI",
                    "MCI",
                    "MCI",
                    "MCI",
                    "MCI",
                    "MCI",
                    "MCI",
                    "MCI",
                    "MCI",
                    "MCI",
                    "MCI",
                    "MCI",
                    "MCI",
                    "MCI",
                    "MCI",
                    "MCI",
                    "MCI",
                    "MCI",
                    "MCI",
                    "MCI",
                    "MCI",
                    "MCI",
                    "MCI",
                    "MCI",
                    "MCI",
                    "MCI",
                    "MCI",
                    "MCI",
                    "MCI",
                    "MCI",
                    "MCI",
                    "MCI",
                    "MCI",
                    "MCI",
                    "MCI",
                    "MCI",
                    "MCI",
                    "MCI",
                    "MCI",
                    "MCI",
                    "MCI",
                    "MCI",
                    "MCI",
                    "MCI",
                    "MCI",
                    "MCI",
                    "MCI",
                    "MCI",
                    "MCI",
                    "AD",
                    "AD",
                    "AD",
                    "AD",
                    "AD",
                    "AD",
                    "AD",
                    "AD",
                    "AD",
                    "AD",
                    "AD",
                    "AD",
                    "AD",
                    "AD",
                    "AD",
                    "AD",
                    "AD",
                    "AD",
                    "AD",
                    "AD",
                    "AD",
                    "AD",
                    "AD",
                    "AD",
                    "AD",
                    "AD",
                    "AD",
                    "AD",
                    "AD",
                    "AD",
                    "AD",
                    "AD",
                    "AD",
                    "AD",
                    "AD",
                    "AD",
                    "AD",
                    "AD",
                    "AD",
                    "AD",
                    "AD",
                    "AD",
                    "AD",
                    "AD",
                    "AD",
                    "AD",
                    "AD",
                    "AD",
                    "AD",
                    "AD"
                ],
                "header": [
                    1.317453,
                    1.345796848,
                    1.374140696,
                    1.402484544,
                    1.430828392,
                    1.45917224,
                    1.487516088,
                    1.515859936,
                    1.544203784,
                    1.572547632,
                    1.60089148,
                    1.629235328,
                    1.657579176,
                    1.685923024,
                    1.7142668719999998,
                    1.7426107199999998,
                    1.7709545679999998,
                    1.7992984159999998,
                    1.8276422639999998,
                    1.8559861119999999,
                    1.8843299599999999,
                    1.9126738079999999,
                    1.9410176559999999,
                    1.9693615039999999,
                    1.9977053519999999,
                    2.0260492,
                    2.0543930479999997,
                    2.0827368959999997,
                    2.1110807439999997,
                    2.1394245919999997,
                    2.1677684399999997,
                    2.1961122879999997,
                    2.2244561359999997,
                    2.2527999839999997,
                    2.2811438319999997,
                    2.3094876799999997,
                    2.3378315279999997,
                    2.3661753759999997,
                    2.3945192239999997,
                    2.4228630719999997,
                    2.4512069199999997,
                    2.4795507679999997,
                    2.5078946159999997,
                    2.5362384639999997,
                    2.5645823119999998,
                    2.5929261599999998,
                    2.6212700079999998,
                    2.6496138559999998,
                    2.6779577039999998,
                    2.7063015519999998,
                    2.7346454,
                    1.317453,
                    1.345796848,
                    1.374140696,
                    1.402484544,
                    1.430828392,
                    1.45917224,
                    1.487516088,
                    1.515859936,
                    1.544203784,
                    1.572547632,
                    1.60089148,
                    1.629235328,
                    1.657579176,
                    1.685923024,
                    1.7142668719999998,
                    1.7426107199999998,
                    1.7709545679999998,
                    1.7992984159999998,
                    1.8276422639999998,
                    1.8559861119999999,
                    1.8843299599999999,
                    1.9126738079999999,
                    1.9410176559999999,
                    1.9693615039999999,
                    1.9977053519999999,
                    2.0260492,
                    2.0543930479999997,
                    2.0827368959999997,
                    2.1110807439999997,
                    2.1394245919999997,
                    2.1677684399999997,
                    2.1961122879999997,
                    2.2244561359999997,
                    2.2527999839999997,
                    2.2811438319999997,
                    2.3094876799999997,
                    2.3378315279999997,
                    2.3661753759999997,
                    2.3945192239999997,
                    2.4228630719999997,
                    2.4512069199999997,
                    2.4795507679999997,
                    2.5078946159999997,
                    2.5362384639999997,
                    2.5645823119999998,
                    2.5929261599999998,
                    2.6212700079999998,
                    2.6496138559999998,
                    2.6779577039999998,
                    2.7063015519999998,
                    2.7346454,
                    1.317453,
                    1.345796848,
                    1.374140696,
                    1.402484544,
                    1.430828392,
                    1.45917224,
                    1.487516088,
                    1.515859936,
                    1.544203784,
                    1.572547632,
                    1.60089148,
                    1.629235328,
                    1.657579176,
                    1.685923024,
                    1.7142668719999998,
                    1.7426107199999998,
                    1.7709545679999998,
                    1.7992984159999998,
                    1.8276422639999998,
                    1.8559861119999999,
                    1.8843299599999999,
                    1.9126738079999999,
                    1.9410176559999999,
                    1.9693615039999999,
                    1.9977053519999999,
                    2.0260492,
                    2.0543930479999997,
                    2.0827368959999997,
                    2.1110807439999997,
                    2.1394245919999997,
                    2.1677684399999997,
                    2.1961122879999997,
                    2.2244561359999997,
                    2.2527999839999997,
                    2.2811438319999997,
                    2.3094876799999997,
                    2.3378315279999997,
                    2.3661753759999997,
                    2.3945192239999997,
                    2.4228630719999997,
                    2.4512069199999997,
                    2.4795507679999997,
                    2.5078946159999997,
                    2.5362384639999997,
                    2.5645823119999998,
                    2.5929261599999998,
                    2.6212700079999998,
                    2.6496138559999998,
                    2.6779577039999998,
                    2.7063015519999998,
                    2.7346454
                ],
                "shape": "vector",
                "value": [
                    0,
                    0,
                    1,
                    0,
                    1,
                    1,
                    2,
                    2,
                    4,
                    4,
                    4,
                    7,
                    8,
                    5,
                    14,
                    14,
                    12,
                    11,
                    17,
                    10,
                    25,
                    11,
                    12,
                    15,
                    15,
                    11,
                    12,
                    13,
                    8,
                    13,
                    3,
                    3,
                    5,
                    4,
                    2,
                    3,
                    4,
                    2,
                    1,
                    1,
                    1,
                    0,
                    1,
                    0,
                    1,
                    0,
                    0,
                    0,
                    0,
                    0,
                    1,
                    0,
                    0,
                    1,
                    1,
                    3,
                    4,
                    5,
                    3,
                    3,
                    3,
                    10,
                    11,
                    20,
                    19,
                    23,
                    29,
                    25,
                    36,
                    35,
                    33,
                    29,
                    38,
                    41,
                    31,
                    24,
                    22,
                    22,
                    24,
                    13,
                    12,
                    16,
                    16,
                    5,
                    12,
                    7,
                    6,
                    5,
                    2,
                    1,
                    3,
                    1,
                    1,
                    1,
                    0,
                    3,
                    0,
                    0,
                    0,
                    0,
                    0,
                    0,
                    1,
                    1,
                    0,
                    0,
                    2,
                    2,
                    8,
                    4,
                    6,
                    6,
                    6,
                    5,
                    11,
                    6,
                    15,
                    8,
                    12,
                    12,
                    16,
                    12,
                    17,
                    14,
                    10,
                    9,
                    6,
                    6,
                    4,
                    6,
                    6,
                    5,
                    3,
                    1,
                    2,
                    3,
                    0,
                    1,
                    3,
                    0,
                    1,
                    0,
                    0,
                    0,
                    0,
                    0,
                    0,
                    0,
                    0,
                    2
                ]
            },
            "name": "Count"
        },
        "label": "Histogram - DX"
    },
    {
        "code": "LeftFOfrontaloperculum",
        "dataType": "DatasetStatistic",
        "dataset": {
            "data": {
                "categories": [
                    "0",
                    "0",
                    "0",
                    "0",
                    "0",
                    "0",
                    "0",
                    "0",
                    "0",
                    "0",
                    "0",
                    "0",
                    "0",
                    "0",
                    "0",
                    "0",
                    "0",
                    "0",
                    "0",
                    "0",
                    "0",
                    "0",
                    "0",
                    "0",
                    "0",
                    "0",
                    "0",
                    "0",
                    "0",
                    "0",
                    "0",
                    "0",
                    "0",
                    "0",
                    "0",
                    "0",
                    "0",
                    "0",
                    "0",
                    "0",
                    "0",
                    "0",
                    "0",
                    "0",
                    "0",
                    "0",
                    "0",
                    "0",
                    "0",
                    "0",
                    "1",
                    "1",
                    "1",
                    "1",
                    "1",
                    "1",
                    "1",
                    "1",
                    "1",
                    "1",
                    "1",
                    "1",
                    "1",
                    "1",
                    "1",
                    "1",
                    "1",
                    "1",
                    "1",
                    "1",
                    "1",
                    "1",
                    "1",
                    "1",
                    "1",
                    "1",
                    "1",
                    "1",
                    "1",
                    "1",
                    "1",
                    "1",
                    "1",
                    "1",
                    "1",
                    "1",
                    "1",
                    "1",
                    "1",
                    "1",
                    "1",
                    "1",
                    "1",
                    "1",
                    "1",
                    "1",
                    "1",
                    "1",
                    "1",
                    "1",
                    "2",
                    "2",
                    "2",
                    "2",
                    "2",
                    "2",
                    "2",
                    "2",
                    "2",
                    "2",
                    "2",
                    "2",
                    "2",
                    "2",
                    "2",
                    "2",
                    "2",
                    "2",
                    "2",
                    "2",
                    "2",
                    "2",
                    "2",
                    "2",
                    "2",
                    "2",
                    "2",
                    "2",
                    "2",
                    "2",
                    "2",
                    "2",
                    "2",
                    "2",
                    "2",
                    "2",
                    "2",
                    "2",
                    "2",
                    "2",
                    "2",
                    "2",
                    "2",
                    "2",
                    "2",
                    "2",
                    "2",
                    "2",
                    "2",
                    "2"
                ],
                "header": [
                    1.317453,
                    1.345796848,
                    1.374140696,
                    1.402484544,
                    1.430828392,
                    1.45917224,
                    1.487516088,
                    1.515859936,
                    1.544203784,
                    1.572547632,
                    1.60089148,
                    1.629235328,
                    1.657579176,
                    1.685923024,
                    1.7142668719999998,
                    1.7426107199999998,
                    1.7709545679999998,
                    1.7992984159999998,
                    1.8276422639999998,
                    1.8559861119999999,
                    1.8843299599999999,
                    1.9126738079999999,
                    1.9410176559999999,
                    1.9693615039999999,
                    1.9977053519999999,
                    2.0260492,
                    2.0543930479999997,
                    2.0827368959999997,
                    2.1110807439999997,
                    2.1394245919999997,
                    2.1677684399999997,
                    2.1961122879999997,
                    2.2244561359999997,
                    2.2527999839999997,
                    2.2811438319999997,
                    2.3094876799999997,
                    2.3378315279999997,
                    2.3661753759999997,
                    2.3945192239999997,
                    2.4228630719999997,
                    2.4512069199999997,
                    2.4795507679999997,
                    2.5078946159999997,
                    2.5362384639999997,
                    2.5645823119999998,
                    2.5929261599999998,
                    2.6212700079999998,
                    2.6496138559999998,
                    2.6779577039999998,
                    2.7063015519999998,
                    2.7346454,
                    1.317453,
                    1.345796848,
                    1.374140696,
                    1.402484544,
                    1.430828392,
                    1.45917224,
                    1.487516088,
                    1.515859936,
                    1.544203784,
                    1.572547632,
                    1.60089148,
                    1.629235328,
                    1.657579176,
                    1.685923024,
                    1.7142668719999998,
                    1.7426107199999998,
                    1.7709545679999998,
                    1.7992984159999998,
                    1.8276422639999998,
                    1.8559861119999999,
                    1.8843299599999999,
                    1.9126738079999999,
                    1.9410176559999999,
                    1.9693615039999999,
                    1.9977053519999999,
                    2.0260492,
                    2.0543930479999997,
                    2.0827368959999997,
                    2.1110807439999997,
                    2.1394245919999997,
                    2.1677684399999997,
                    2.1961122879999997,
                    2.2244561359999997,
                    2.2527999839999997,
                    2.2811438319999997,
                    2.3094876799999997,
                    2.3378315279999997,
                    2.3661753759999997,
                    2.3945192239999997,
                    2.4228630719999997,
                    2.4512069199999997,
                    2.4795507679999997,
                    2.5078946159999997,
                    2.5362384639999997,
                    2.5645823119999998,
                    2.5929261599999998,
                    2.6212700079999998,
                    2.6496138559999998,
                    2.6779577039999998,
                    2.7063015519999998,
                    2.7346454,
                    1.317453,
                    1.345796848,
                    1.374140696,
                    1.402484544,
                    1.430828392,
                    1.45917224,
                    1.487516088,
                    1.515859936,
                    1.544203784,
                    1.572547632,
                    1.60089148,
                    1.629235328,
                    1.657579176,
                    1.685923024,
                    1.7142668719999998,
                    1.7426107199999998,
                    1.7709545679999998,
                    1.7992984159999998,
                    1.8276422639999998,
                    1.8559861119999999,
                    1.8843299599999999,
                    1.9126738079999999,
                    1.9410176559999999,
                    1.9693615039999999,
                    1.9977053519999999,
                    2.0260492,
                    2.0543930479999997,
                    2.0827368959999997,
                    2.1110807439999997,
                    2.1394245919999997,
                    2.1677684399999997,
                    2.1961122879999997,
                    2.2244561359999997,
                    2.2527999839999997,
                    2.2811438319999997,
                    2.3094876799999997,
                    2.3378315279999997,
                    2.3661753759999997,
                    2.3945192239999997,
                    2.4228630719999997,
                    2.4512069199999997,
                    2.4795507679999997,
                    2.5078946159999997,
                    2.5362384639999997,
                    2.5645823119999998,
                    2.5929261599999998,
                    2.6212700079999998,
                    2.6496138559999998,
                    2.6779577039999998,
                    2.7063015519999998,
                    2.7346454
                ],
                "shape": "vector",
                "value": [
                    0,
                    0,
                    1,
                    0,
                    1,
                    2,
                    5,
                    4,
                    7,
                    5,
                    6,
                    9,
                    10,
                    15,
                    27,
                    20,
                    25,
                    29,
                    33,
                    37,
                    38,
                    31,
                    31,
                    39,
                    26,
                    17,
                    22,
                    18,
                    21,
                    19,
                    9,
                    10,
                    10,
                    6,
                    7,
                    5,
                    6,
                    4,
                    1,
                    1,
                    2,
                    0,
                    1,
                    0,
                    1,
                    2,
                    0,
                    0,
                    0,
                    1,
                    1,
                    0,
                    0,
                    2,
                    1,
                    2,
                    2,
                    3,
                    6,
                    5,
                    6,
                    11,
                    9,
                    11,
                    14,
                    17,
                    22,
                    13,
                    27,
                    14,
                    29,
                    17,
                    25,
                    24,
                    25,
                    17,
                    10,
                    15,
                    10,
                    12,
                    7,
                    10,
                    13,
                    3,
                    6,
                    6,
                    3,
                    3,
                    3,
                    0,
                    3,
                    1,
                    1,
                    1,
                    0,
                    1,
                    0,
                    0,
                    0,
                    1,
                    0,
                    0,
                    1,
                    0,
                    0,
                    0,
                    1,
                    2,
                    2,
                    1,
                    1,
                    3,
                    6,
                    4,
                    3,
                    6,
                    9,
                    2,
                    5,
                    6,
                    6,
                    4,
                    11,
                    6,
                    5,
                    10,
                    8,
                    7,
                    5,
                    0,
                    5,
                    4,
                    1,
                    1,
                    3,
                    2,
                    0,
                    1,
                    2,
                    1,
                    0,
                    0,
                    0,
                    0,
                    0,
                    0,
                    0,
                    0,
                    0,
                    0
                ]
            },
            "name": "Count"
        },
        "label": "Histogram - APOE4"
    },
    {
        "code": "LeftFOfrontaloperculum",
        "dataType": "DatasetStatistic",
        "dataset": {
            "data": {
                "categories": [
                    "-50y",
                    "-50y",
                    "-50y",
                    "-50y",
                    "-50y",
                    "-50y",
                    "-50y",
                    "-50y",
                    "-50y",
                    "-50y",
                    "-50y",
                    "-50y",
                    "-50y",
                    "-50y",
                    "-50y",
                    "-50y",
                    "-50y",
                    "-50y",
                    "-50y",
                    "-50y",
                    "-50y",
                    "-50y",
                    "-50y",
                    "-50y",
                    "-50y",
                    "-50y",
                    "-50y",
                    "-50y",
                    "-50y",
                    "-50y",
                    "-50y",
                    "-50y",
                    "-50y",
                    "-50y",
                    "-50y",
                    "-50y",
                    "-50y",
                    "-50y",
                    "-50y",
                    "-50y",
                    "-50y",
                    "-50y",
                    "-50y",
                    "-50y",
                    "-50y",
                    "-50y",
                    "-50y",
                    "-50y",
                    "-50y",
                    "-50y",
                    "50-59y",
                    "50-59y",
                    "50-59y",
                    "50-59y",
                    "50-59y",
                    "50-59y",
                    "50-59y",
                    "50-59y",
                    "50-59y",
                    "50-59y",
                    "50-59y",
                    "50-59y",
                    "50-59y",
                    "50-59y",
                    "50-59y",
                    "50-59y",
                    "50-59y",
                    "50-59y",
                    "50-59y",
                    "50-59y",
                    "50-59y",
                    "50-59y",
                    "50-59y",
                    "50-59y",
                    "50-59y",
                    "50-59y",
                    "50-59y",
                    "50-59y",
                    "50-59y",
                    "50-59y",
                    "50-59y",
                    "50-59y",
                    "50-59y",
                    "50-59y",
                    "50-59y",
                    "50-59y",
                    "50-59y",
                    "50-59y",
                    "50-59y",
                    "50-59y",
                    "50-59y",
                    "50-59y",
                    "50-59y",
                    "50-59y",
                    "50-59y",
                    "50-59y",
                    "50-59y",
                    "50-59y",
                    "50-59y",
                    "50-59y",
                    "60-69y",
                    "60-69y",
                    "60-69y",
                    "60-69y",
                    "60-69y",
                    "60-69y",
                    "60-69y",
                    "60-69y",
                    "60-69y",
                    "60-69y",
                    "60-69y",
                    "60-69y",
                    "60-69y",
                    "60-69y",
                    "60-69y",
                    "60-69y",
                    "60-69y",
                    "60-69y",
                    "60-69y",
                    "60-69y",
                    "60-69y",
                    "60-69y",
                    "60-69y",
                    "60-69y",
                    "60-69y",
                    "60-69y",
                    "60-69y",
                    "60-69y",
                    "60-69y",
                    "60-69y",
                    "60-69y",
                    "60-69y",
                    "60-69y",
                    "60-69y",
                    "60-69y",
                    "60-69y",
                    "60-69y",
                    "60-69y",
                    "60-69y",
                    "60-69y",
                    "60-69y",
                    "60-69y",
                    "60-69y",
                    "60-69y",
                    "60-69y",
                    "60-69y",
                    "60-69y",
                    "60-69y",
                    "60-69y",
                    "60-69y",
                    "70-79y",
                    "70-79y",
                    "70-79y",
                    "70-79y",
                    "70-79y",
                    "70-79y",
                    "70-79y",
                    "70-79y",
                    "70-79y",
                    "70-79y",
                    "70-79y",
                    "70-79y",
                    "70-79y",
                    "70-79y",
                    "70-79y",
                    "70-79y",
                    "70-79y",
                    "70-79y",
                    "70-79y",
                    "70-79y",
                    "70-79y",
                    "70-79y",
                    "70-79y",
                    "70-79y",
                    "70-79y",
                    "70-79y",
                    "70-79y",
                    "70-79y",
                    "70-79y",
                    "70-79y",
                    "70-79y",
                    "70-79y",
                    "70-79y",
                    "70-79y",
                    "70-79y",
                    "70-79y",
                    "70-79y",
                    "70-79y",
                    "70-79y",
                    "70-79y",
                    "70-79y",
                    "70-79y",
                    "70-79y",
                    "70-79y",
                    "70-79y",
                    "70-79y",
                    "70-79y",
                    "70-79y",
                    "70-79y",
                    "70-79y",
                    "+80y",
                    "+80y",
                    "+80y",
                    "+80y",
                    "+80y",
                    "+80y",
                    "+80y",
                    "+80y",
                    "+80y",
                    "+80y",
                    "+80y",
                    "+80y",
                    "+80y",
                    "+80y",
                    "+80y",
                    "+80y",
                    "+80y",
                    "+80y",
                    "+80y",
                    "+80y",
                    "+80y",
                    "+80y",
                    "+80y",
                    "+80y",
                    "+80y",
                    "+80y",
                    "+80y",
                    "+80y",
                    "+80y",
                    "+80y",
                    "+80y",
                    "+80y",
                    "+80y",
                    "+80y",
                    "+80y",
                    "+80y",
                    "+80y",
                    "+80y",
                    "+80y",
                    "+80y",
                    "+80y",
                    "+80y",
                    "+80y",
                    "+80y",
                    "+80y",
                    "+80y",
                    "+80y",
                    "+80y",
                    "+80y",
                    "+80y"
                ],
                "header": [
                    1.317453,
                    1.345796848,
                    1.374140696,
                    1.402484544,
                    1.430828392,
                    1.45917224,
                    1.487516088,
                    1.515859936,
                    1.544203784,
                    1.572547632,
                    1.60089148,
                    1.629235328,
                    1.657579176,
                    1.685923024,
                    1.7142668719999998,
                    1.7426107199999998,
                    1.7709545679999998,
                    1.7992984159999998,
                    1.8276422639999998,
                    1.8559861119999999,
                    1.8843299599999999,
                    1.9126738079999999,
                    1.9410176559999999,
                    1.9693615039999999,
                    1.9977053519999999,
                    2.0260492,
                    2.0543930479999997,
                    2.0827368959999997,
                    2.1110807439999997,
                    2.1394245919999997,
                    2.1677684399999997,
                    2.1961122879999997,
                    2.2244561359999997,
                    2.2527999839999997,
                    2.2811438319999997,
                    2.3094876799999997,
                    2.3378315279999997,
                    2.3661753759999997,
                    2.3945192239999997,
                    2.4228630719999997,
                    2.4512069199999997,
                    2.4795507679999997,
                    2.5078946159999997,
                    2.5362384639999997,
                    2.5645823119999998,
                    2.5929261599999998,
                    2.6212700079999998,
                    2.6496138559999998,
                    2.6779577039999998,
                    2.7063015519999998,
                    2.7346454,
                    1.317453,
                    1.345796848,
                    1.374140696,
                    1.402484544,
                    1.430828392,
                    1.45917224,
                    1.487516088,
                    1.515859936,
                    1.544203784,
                    1.572547632,
                    1.60089148,
                    1.629235328,
                    1.657579176,
                    1.685923024,
                    1.7142668719999998,
                    1.7426107199999998,
                    1.7709545679999998,
                    1.7992984159999998,
                    1.8276422639999998,
                    1.8559861119999999,
                    1.8843299599999999,
                    1.9126738079999999,
                    1.9410176559999999,
                    1.9693615039999999,
                    1.9977053519999999,
                    2.0260492,
                    2.0543930479999997,
                    2.0827368959999997,
                    2.1110807439999997,
                    2.1394245919999997,
                    2.1677684399999997,
                    2.1961122879999997,
                    2.2244561359999997,
                    2.2527999839999997,
                    2.2811438319999997,
                    2.3094876799999997,
                    2.3378315279999997,
                    2.3661753759999997,
                    2.3945192239999997,
                    2.4228630719999997,
                    2.4512069199999997,
                    2.4795507679999997,
                    2.5078946159999997,
                    2.5362384639999997,
                    2.5645823119999998,
                    2.5929261599999998,
                    2.6212700079999998,
                    2.6496138559999998,
                    2.6779577039999998,
                    2.7063015519999998,
                    2.7346454,
                    1.317453,
                    1.345796848,
                    1.374140696,
                    1.402484544,
                    1.430828392,
                    1.45917224,
                    1.487516088,
                    1.515859936,
                    1.544203784,
                    1.572547632,
                    1.60089148,
                    1.629235328,
                    1.657579176,
                    1.685923024,
                    1.7142668719999998,
                    1.7426107199999998,
                    1.7709545679999998,
                    1.7992984159999998,
                    1.8276422639999998,
                    1.8559861119999999,
                    1.8843299599999999,
                    1.9126738079999999,
                    1.9410176559999999,
                    1.9693615039999999,
                    1.9977053519999999,
                    2.0260492,
                    2.0543930479999997,
                    2.0827368959999997,
                    2.1110807439999997,
                    2.1394245919999997,
                    2.1677684399999997,
                    2.1961122879999997,
                    2.2244561359999997,
                    2.2527999839999997,
                    2.2811438319999997,
                    2.3094876799999997,
                    2.3378315279999997,
                    2.3661753759999997,
                    2.3945192239999997,
                    2.4228630719999997,
                    2.4512069199999997,
                    2.4795507679999997,
                    2.5078946159999997,
                    2.5362384639999997,
                    2.5645823119999998,
                    2.5929261599999998,
                    2.6212700079999998,
                    2.6496138559999998,
                    2.6779577039999998,
                    2.7063015519999998,
                    2.7346454,
                    1.317453,
                    1.345796848,
                    1.374140696,
                    1.402484544,
                    1.430828392,
                    1.45917224,
                    1.487516088,
                    1.515859936,
                    1.544203784,
                    1.572547632,
                    1.60089148,
                    1.629235328,
                    1.657579176,
                    1.685923024,
                    1.7142668719999998,
                    1.7426107199999998,
                    1.7709545679999998,
                    1.7992984159999998,
                    1.8276422639999998,
                    1.8559861119999999,
                    1.8843299599999999,
                    1.9126738079999999,
                    1.9410176559999999,
                    1.9693615039999999,
                    1.9977053519999999,
                    2.0260492,
                    2.0543930479999997,
                    2.0827368959999997,
                    2.1110807439999997,
                    2.1394245919999997,
                    2.1677684399999997,
                    2.1961122879999997,
                    2.2244561359999997,
                    2.2527999839999997,
                    2.2811438319999997,
                    2.3094876799999997,
                    2.3378315279999997,
                    2.3661753759999997,
                    2.3945192239999997,
                    2.4228630719999997,
                    2.4512069199999997,
                    2.4795507679999997,
                    2.5078946159999997,
                    2.5362384639999997,
                    2.5645823119999998,
                    2.5929261599999998,
                    2.6212700079999998,
                    2.6496138559999998,
                    2.6779577039999998,
                    2.7063015519999998,
                    2.7346454,
                    1.317453,
                    1.345796848,
                    1.374140696,
                    1.402484544,
                    1.430828392,
                    1.45917224,
                    1.487516088,
                    1.515859936,
                    1.544203784,
                    1.572547632,
                    1.60089148,
                    1.629235328,
                    1.657579176,
                    1.685923024,
                    1.7142668719999998,
                    1.7426107199999998,
                    1.7709545679999998,
                    1.7992984159999998,
                    1.8276422639999998,
                    1.8559861119999999,
                    1.8843299599999999,
                    1.9126738079999999,
                    1.9410176559999999,
                    1.9693615039999999,
                    1.9977053519999999,
                    2.0260492,
                    2.0543930479999997,
                    2.0827368959999997,
                    2.1110807439999997,
                    2.1394245919999997,
                    2.1677684399999997,
                    2.1961122879999997,
                    2.2244561359999997,
                    2.2527999839999997,
                    2.2811438319999997,
                    2.3094876799999997,
                    2.3378315279999997,
                    2.3661753759999997,
                    2.3945192239999997,
                    2.4228630719999997,
                    2.4512069199999997,
                    2.4795507679999997,
                    2.5078946159999997,
                    2.5362384639999997,
                    2.5645823119999998,
                    2.5929261599999998,
                    2.6212700079999998,
                    2.6496138559999998,
                    2.6779577039999998,
                    2.7063015519999998,
                    2.7346454
                ],
                "shape": "vector",
                "value": [
                    0,
                    0,
                    0,
                    0,
                    0,
                    0,
                    0,
                    0,
                    0,
                    0,
                    0,
                    0,
                    0,
                    0,
                    0,
                    0,
                    0,
                    0,
                    0,
                    0,
                    0,
                    0,
                    0,
                    0,
                    0,
                    0,
                    0,
                    0,
                    0,
                    0,
                    0,
                    0,
                    0,
                    0,
                    0,
                    0,
                    0,
                    0,
                    0,
                    0,
                    0,
                    0,
                    0,
                    0,
                    0,
                    0,
                    0,
                    0,
                    0,
                    0,
                    0,
                    0,
                    0,
                    0,
                    0,
                    0,
                    1,
                    3,
                    1,
                    0,
                    1,
                    1,
                    0,
                    1,
                    0,
                    2,
                    3,
                    3,
                    3,
                    2,
                    0,
                    4,
                    1,
                    2,
                    2,
                    1,
                    1,
                    1,
                    3,
                    2,
                    0,
                    1,
                    3,
                    1,
                    0,
                    1,
                    2,
                    0,
                    0,
                    0,
                    1,
                    0,
                    0,
                    0,
                    0,
                    0,
                    0,
                    0,
                    0,
                    0,
                    0,
                    0,
                    0,
                    1,
                    0,
                    2,
                    0,
                    1,
                    2,
                    3,
                    2,
                    5,
                    6,
                    9,
                    8,
                    6,
                    10,
                    4,
                    15,
                    14,
                    15,
                    18,
                    16,
                    20,
                    11,
                    12,
                    13,
                    9,
                    9,
                    8,
                    4,
                    9,
                    9,
                    2,
                    5,
                    2,
                    2,
                    5,
                    1,
                    1,
                    1,
                    0,
                    0,
                    0,
                    0,
                    2,
                    0,
                    0,
                    0,
                    0,
                    1,
                    0,
                    2,
                    1,
                    2,
                    1,
                    5,
                    2,
                    6,
                    8,
                    6,
                    11,
                    12,
                    13,
                    25,
                    21,
                    26,
                    26,
                    38,
                    29,
                    38,
                    24,
                    36,
                    37,
                    29,
                    23,
                    15,
                    23,
                    18,
                    18,
                    10,
                    11,
                    10,
                    5,
                    8,
                    9,
                    5,
                    3,
                    4,
                    0,
                    2,
                    1,
                    2,
                    1,
                    1,
                    0,
                    0,
                    0,
                    0,
                    2,
                    0,
                    0,
                    0,
                    0,
                    0,
                    1,
                    2,
                    3,
                    6,
                    0,
                    4,
                    6,
                    7,
                    7,
                    11,
                    14,
                    17,
                    11,
                    9,
                    12,
                    21,
                    6,
                    14,
                    11,
                    14,
                    8,
                    11,
                    8,
                    6,
                    4,
                    7,
                    3,
                    2,
                    2,
                    3,
                    1,
                    1,
                    0,
                    1,
                    1,
                    1,
                    0,
                    0,
                    0,
                    0,
                    1,
                    0,
                    0,
                    0,
                    0
                ]
            },
            "name": "Count"
        },
        "label": "Histogram - AgeGroup"
    }
]