[
    {
        "average": 6.4352825695964135,
        "code": "RightIOGinferioroccipitalgyrus",
        "count": 1115,
        "dataType": "SummaryStatistics",
        "max": 9.7815647,
        "min": 4.0437126,
        "std": 0.7963451212851043
    },
    {
        "code": "RightIOGinferioroccipitalgyrus",
        "dataType": "DatasetStatistic",
        "dataset": {
            "data": {
                "category": [],
                "header": [
                    4.0437126,
                    4.158469642,
                    4.273226684,
                    4.387983726,
                    4.502740768,
                    4.61749781,
                    4.7322548520000005,
                    4.847011894,
                    4.961768936,
                    5.076525978,
                    5.19128302,
                    5.306040062,
                    5.420797104,
                    5.535554146,
                    5.650311188,
                    5.765068230000001,
                    5.879825272,
                    5.9945823140000005,
                    6.1093393559999996,
                    6.224096398,
                    6.33885344,
                    6.453610482,
                    6.568367524,
                    6.683124566,
                    6.797881608,
                    6.91263865,
                    7.027395692000001,
                    7.142152734,
                    7.2569097760000005,
                    7.371666818,
                    7.48642386,
                    7.601180902,
                    7.715937944,
                    7.830694986,
                    7.945452028,
                    8.060209069999999,
                    8.174966112,
                    8.289723154,
                    8.404480196000002,
                    8.519237238,
                    8.63399428,
                    8.748751322,
                    8.863508364000001,
                    8.978265406,
                    9.093022448,
                    9.20777949,
                    9.322536532,
                    9.437293574,
                    9.552050615999999,
                    9.666807658,
                    9.7815647
                ],
                "shape": "vector",
                "value": [
                    1,
                    1,
                    2,
                    2,
                    3,
                    5,
                    6,
                    9,
                    11,
                    17,
                    19,
                    43,
                    26,
                    39,
                    34,
                    44,
                    64,
                    70,
                    64,
                    58,
                    69,
                    55,
                    55,
                    67,
                    57,
                    43,
                    45,
                    30,
                    40,
                    27,
                    26,
                    25,
                    12,
                    11,
                    10,
                    5,
                    5,
                    4,
                    3,
                    2,
                    2,
                    0,
                    1,
                    1,
                    1,
                    0,
                    0,
                    0,
                    0,
                    1
                ]
            },
            "name": "Count"
        },
        "label": "Histogram"
    }
]